[
    {
        "empresa": "DevCrash",
        "nombre": "Carlos",
        "curso": "HTML5, CSS3, JavaScript para principiantes",
        "price": 150
    },
    {
        "empresa": "DevCrash",
        "nombre": "Carlos",
        "curso": "Curso comida vegetariana",
        "price": 100
    },
    {
        "empresa": "DevCrash",
        "nombre": "Carlos",
        "curso": "Guitarra para principiantes",
        "price": 130
    },
    {
        "empresa": "DevCrash",
        "nombre": "Carlos",
        "curso": "Huerto para tu casa",
        "price": 200
    },
    {
        "empresa": "DevCrash",
        "nombre": "Carlos",
        "curso": "Decoracion con productos de tu hogar",
        "price": 100
    },
    {
        "empresa": "DevCrash",
        "nombre": "Carlos",
        "curso": "Curso de costura para principiantes",
        "price": 300
    },
    {
        "empresa": "DevCrash",
        "nombre": "Carlos",
        "curso": "Curso para reparar tu PC",
        "price": 500
    },
    {
        "empresa": "DevCrash",
        "nombre": "Carlos",
        "curso": "Curso de diseño ",
        "price": 350
    },
    {
        "empresa": "DevCrash",
        "nombre": "Carlos",
        "curso": "Curso de finanzas para principiantes",
        "price": 200
    }
]